rustique-0.1.0.dist-info/METADATA
rustique-0.1.0.dist-info/WHEEL
rustique/primitives/__init__.py
rustique/experiments/vector.py
rustique/experiments/main.py
rustique/experiments/speed.py
rustique/experiments/wtf.py
rustique/experiments/abc.py
rustique/py.typed
rustique/__init__.py
rustique/collections/dict.py
rustique/collections/list.py
rustique/collections/__init__.py
rustique/rustique.pyi
rustique/rustique.cpython-311-x86_64-linux-gnu.so
rustique-0.1.0.dist-info/RECORD
